vc/__init__.py
vc/init_vc.py
vc/settings.py
vc/client/__init__.py
vc/client/schemas_base.py
vc/client/soldo/__init__.py
vc/client/soldo/client.py
vc/client/soldo/requesters/__init__.py
vc/client/soldo/requesters/requester_base.py
vc/client/soldo/requesters/schema_base.py
vc/client/soldo/requesters/schemas.py
vc/client/soldo/requesters/utils.py
vc/db/__init__.py
vc/db/base_class.py
vc/db/models.py
vc/libs/__init__.py
vc/libs/decoratos.py
vc/libs/utils.py
vc/manager/__init__.py
vc/manager/base.py
vc/manager/soldo.py
vc/manager/soldo_event.py
vc/models/__init__.py
vc/models/base.py
vc/models/soldo.py
virtual_cards-0.0.35.dist-info/METADATA
virtual_cards-0.0.35.dist-info/WHEEL
virtual_cards-0.0.35.dist-info/top_level.txt
virtual_cards-0.0.35.dist-info/RECORD
